setup.py
imgnet/__init__.py
imgnet/main.py
imgnet.egg-info/PKG-INFO
imgnet.egg-info/SOURCES.txt
imgnet.egg-info/dependency_links.txt
imgnet.egg-info/entry_points.txt
imgnet.egg-info/requires.txt
imgnet.egg-info/top_level.txt
imgnet/imgnet_engine/__init__.py
imgnet/imgnet_engine/classification/__init__.py
imgnet/imgnet_engine/classification/imgnet_classification.py
imgnet/imgnet_engine/classification/predict.py
imgnet/imgnet_engine/classification/train_engine.py
imgnet/imgnet_tools/__init__.py
imgnet/imgnet_tools/all_encryption.py
imgnet/imgnet_utils/__init__.py
imgnet/imgnet_utils/callbacks.py
imgnet/imgnet_utils/common_utils.py
imgnet/imgnet_utils/config.py
imgnet/imgnet_utils/data_manager.py
imgnet/imgnet_utils/model.py
imgnet/imgnet_utils/models_config.py