Metadata-Version: 2.1
Name: imgnet
Version: 0.1
Summary: Its an auto image classification library
Home-page: https://github.com/srnsrn120/imgnet-Package
Author: Soumyaranjan Nayak
Author-email: srnsrn120@gmail.com
License: MIT
Keywords: imgnet
Platform: UNKNOWN
Classifier: Development Status :: 3 - Alpha
Classifier: Intended Audience :: Developers
Classifier: Topic :: Software Development :: Build Tools
Classifier: License :: OSI Approved :: MIT License
Classifier: Programming Language :: Python :: 3
Classifier: Programming Language :: Python :: 3.4
Classifier: Programming Language :: Python :: 3.5
Classifier: Programming Language :: Python :: 3.6
